memory_mcp/__init__.py
memory_mcp/cli.py
memory_mcp/config.py
memory_mcp/embeddings.py
memory_mcp/helpers.py
memory_mcp/logging.py
memory_mcp/metrics.py
memory_mcp/migrations.py
memory_mcp/mining.py
memory_mcp/ml_classification.py
memory_mcp/models.py
memory_mcp/project.py
memory_mcp/redaction.py
memory_mcp/responses.py
memory_mcp/text_parsing.py
memory_mcp/dashboard/__init__.py
memory_mcp/dashboard/app.py
memory_mcp/dashboard/templates/base.html
memory_mcp/dashboard/templates/graph.html
memory_mcp/dashboard/templates/hot_cache.html
memory_mcp/dashboard/templates/index.html
memory_mcp/dashboard/templates/injections.html
memory_mcp/dashboard/templates/memories.html
memory_mcp/dashboard/templates/mining.html
memory_mcp/dashboard/templates/session_detail.html
memory_mcp/dashboard/templates/sessions.html
memory_mcp/dashboard/templates/partials/hot_item.html
memory_mcp/dashboard/templates/partials/hot_list.html
memory_mcp/dashboard/templates/partials/injection_table.html
memory_mcp/dashboard/templates/partials/memory_row.html
memory_mcp/dashboard/templates/partials/memory_table.html
memory_mcp/dashboard/templates/partials/stats_cards.html
memory_mcp/server/__init__.py
memory_mcp/server/app.py
memory_mcp/server/tools/__init__.py
memory_mcp/server/tools/cold_storage.py
memory_mcp/server/tools/consolidation.py
memory_mcp/server/tools/contradictions.py
memory_mcp/server/tools/hot_cache.py
memory_mcp/server/tools/maintenance.py
memory_mcp/server/tools/mining.py
memory_mcp/server/tools/predictions.py
memory_mcp/server/tools/relationships.py
memory_mcp/server/tools/retrieval.py
memory_mcp/server/tools/seeding.py
memory_mcp/server/tools/sessions.py
memory_mcp/server/tools/trust.py
memory_mcp/storage/__init__.py
memory_mcp/storage/audit.py
memory_mcp/storage/bootstrap.py
memory_mcp/storage/consolidation.py
memory_mcp/storage/contradictions.py
memory_mcp/storage/core.py
memory_mcp/storage/hot_cache.py
memory_mcp/storage/injection_tracking.py
memory_mcp/storage/maintenance.py
hot_memory_mcp-0.7.3.dist-info/METADATA
hot_memory_mcp-0.7.3.dist-info/WHEEL
hot_memory_mcp-0.7.3.dist-info/entry_points.txt
hot_memory_mcp-0.7.3.dist-info/licenses/LICENSE
hot_memory_mcp-0.7.3.dist-info/RECORD
