Metadata-Version: 2.4
Name: hot-memory-mcp
Version: 0.7.3
Summary: Engram-inspired memory MCP server with hot cache and pattern mining
Project-URL: Homepage, https://github.com/michael-denyer/memory-mcp
Project-URL: Repository, https://github.com/michael-denyer/memory-mcp
Project-URL: Issues, https://github.com/michael-denyer/memory-mcp/issues
Author: Memory MCP Contributors
License-Expression: MIT
License-File: LICENSE
Classifier: Development Status :: 4 - Beta
Classifier: Intended Audience :: Developers
Classifier: License :: OSI Approved :: MIT License
Classifier: Programming Language :: Python :: 3
Classifier: Programming Language :: Python :: 3.10
Classifier: Programming Language :: Python :: 3.11
Classifier: Programming Language :: Python :: 3.12
Requires-Python: >=3.10
Requires-Dist: click<9,>=8.0
Requires-Dist: fastapi<1,>=0.100
Requires-Dist: fastmcp<3,>=2.0
Requires-Dist: jinja2<4,>=3.0
Requires-Dist: loguru<1,>=0.7
Requires-Dist: mlx-embeddings>=0.0.5; sys_platform == 'darwin' and platform_machine == 'arm64'
Requires-Dist: pydantic-settings<3,>=2.0
Requires-Dist: pydantic<3,>=2.0
Requires-Dist: rich<14,>=13.0
Requires-Dist: sentence-transformers<4,>=3.0
Requires-Dist: sqlite-vec<1,>=0.1
Requires-Dist: transformers<5,>=4.0
Requires-Dist: uvicorn[standard]<1,>=0.20
Provides-Extra: mlx
Requires-Dist: mlx-embeddings>=0.0.5; extra == 'mlx'
